calculate_tool_lengyue1084/__init__.py
calculate_tool_lengyue1084/main.py
calculate_tool_lengyue1084-0.3.15.dist-info/licenses/LICENSE
calculate_tool_lengyue1084-0.3.15.dist-info/METADATA
calculate_tool_lengyue1084-0.3.15.dist-info/WHEEL
calculate_tool_lengyue1084-0.3.15.dist-info/entry_points.txt
calculate_tool_lengyue1084-0.3.15.dist-info/top_level.txt
calculate_tool_lengyue1084-0.3.15.dist-info/RECORD
