Metadata-Version: 2.4
Name: calculate-tool-lengyue1084
Version: 0.3.15
Summary: 一个简单的计算工具包，提供基本的数学运算和问候功能
Author-email: lengyue1084 <95695864@qq.com>
License: Copyright (c) 2018 The Python Packaging Authority
Requires-Python: >=3.12
License-File: LICENSE
Requires-Dist: mcp
Dynamic: license-file
